[{"name": "Beta-Space", "apistate": "0.13", "url": "http://status.kreativitaet-trifft-technik.de/status.json"}, {"name": "Apollo-NG", "apistate": "0.12", "url": "https://apollo.open-resource.org/status.php"}, {"name": "/dev/tal", "apistate": "0.13", "url": "https://www.devtal.de/api/"}, {"name": "Attraktor Makerspace", "apistate": "0.13", "url": "http://blog.attraktor.org/spaceapi/spaceapi.json"}, {"name": "Bytespeicher", "apistate": "0.13", "url": "http://status.bytespeicher.org/status.json"}, {"name": "Breizh-Entropy", "apistate": "0.13", "url": "http://breizh-entropy.org/spaceapi.json"}, {"name": "ACKspace", "apistate": "0.13", "url": "https://ackspace.nl/spaceAPI/"}, {"name": "Binary Kitchen", "apistate": "0.13", "url": "https://www.binary-kitchen.de/spaceapi.php"}, {"name": "AFRA", "apistate": "0.13", "url": "https://spaceapi.afra-berlin.de/v1/status.json"}, {"name": "57North Hacklab", "apistate": "0.13", "url": "http://57north.co/spaceapi"}, {"name": "Bitlair", "apistate": "0.13", "url": "https://bitlair.nl/statejson.php"}, {"name": "CCC Aachen", "apistate": "0.13", "url": "https://status.aachen.ccc.de/spaceapi"}, {"name": "CCC Hamburg", "apistate": "0.13", "url": "https://hamburg.ccc.de/dooris/status.json"}, {"name": "Chaostreff Z\u00c3\u00bcrich", "apistate": "0.13", "url": "https://www.ccczh.ch/api/v13/"}, {"name": "DevLoL", "apistate": "0.13", "url": "https://devlol.org/status/hackerspaceapi/"}, {"name": "Chaos Darmstadt", "apistate": "0.12", "url": "http://api.chaos-darmstadt.de/json"}, {"name": "Chaostreff Bern", "apistate": "0.13", "url": "https://www.chaosbern.ch/spaceapi.json"}, {"name": "Brixel", "apistate": "0.13", "url": "https://spaceapi.azurewebsites.net/api/Status"}, {"name": "CCC Cologne", "apistate": "0.13", "url": "https://api.koeln.ccc.de"}, {"name": "Chaostreff Flensburg", "apistate": "0.13", "url": "https://api.chaostreff-flensburg.de/"}, {"name": "Chaosdorf", "apistate": "0.13", "url": "https://chaosdorf.de/space_api.json"}, {"name": "Chaospott", "apistate": "0.13", "url": "https://status.chaospott.de/status.json"}, {"name": "Chaostreff Salzburg", "apistate": "0.13", "url": "https://spaceapi.sbg.chaostreff.at/status/json"}, {"name": "/usr/space", "apistate": "0.13", "url": "https://usrspace.at/spaceapi"}, {"name": "Chaostreff Basel", "apistate": "invalid", "url": "https://wiki.kabelsalat.ch/spaceapi/"}, {"name": "Freiraum", "apistate": "not available", "url": "http://hackerspace-ulm.de/status.json"}, {"name": "Das Labor", "apistate": "0.13", "url": "https://das-labor.org/status/api"}, {"name": "Dlabs Hackerspace", "apistate": "not available", "url": "http://www.dlabs.co/api.php"}, {"name": "Eigenbaukombinat Halle", "apistate": "0.13", "url": "http://api.terminal21.de/status_ebk.json"}, {"name": "CCC Mannheim", "apistate": "0.13", "url": "https://www.ccc-mannheim.de/spaceapi/spaceapi.json"}, {"name": "Coredump", "apistate": "0.13", "url": "https://status.crdmp.ch/"}, {"name": "ChaosStuff", "apistate": "0.13", "url": "https://spaceapi.c3l.lu/status.json"}, {"name": "Chaostreff Recklinghausen c3RE", "apistate": "0.13", "url": "http://doorstatus.c3re.de/status/json"}, {"name": "FabLab N\u00fcrnberg", "apistate": "0.13", "url": "http://api.fablab-nuernberg.de/spaceapi.php"}, {"name": "Chaostreff-Dortmund", "apistate": "0.13", "url": "http://status.ctdo.de/api/spaceapi/v13"}, {"name": "Entropia", "apistate": "0.13", "url": "http://club.entropia.de/spaceapi"}, {"name": "CADR", "apistate": "not available", "url": "http://cadrspace.ru/status/json"}, {"name": "Chaosconsulting", "apistate": "0.13", "url": "http://chaos-consulting.de/api/space.api"}, {"name": "FabLab Neustadt a. d. Aisch - Bad Windsheim", "apistate": "not available", "url": "https://www.fablab-nea.de/status/json"}, {"name": "BinarySpace", "apistate": "not available", "url": "http://www.binaryspace.co.za/status/status.php"}, {"name": "CCCFr", "apistate": "0.13", "url": "http://cccfr.de/status/spaceapi.py"}, {"name": "Edinburgh Hacklab", "apistate": "0.13", "url": "http://spaceapi.edinburghhacklab.com/spaceapi.json"}, {"name": "K4CG", "apistate": "invalid", "url": "http://spaceapi.k4cg.org/spaceapi.json"}, {"name": "Frack", "apistate": "0.13", "url": "http://frack.nl/spacestate/?api"}, {"name": "Hack42", "apistate": "0.13", "url": "http://hack42.nl/spacestate/json.php"}, {"name": "HTU Graz - Makerspace", "apistate": "0.13", "url": "http://edv-support.htu.tugraz.at/doorothy/mkrspc/status.spaceapi"}, {"name": "dezentrale", "apistate": "not available", "url": "https://dezentrale.space/api/status.json"}, {"name": "Terminal.21 Basislager", "apistate": "0.13", "url": "http://api.terminal21.de"}, {"name": "Hackerspace Bielefeld e.V.", "apistate": "0.13", "url": "https://hackerspace-bielefeld.de/spacestatus/status.json"}, {"name": "HTU Graz - PhiLab", "apistate": "0.13", "url": "http://edv-support.htu.tugraz.at/doorothy/philab/status.spaceapi"}, {"name": "Post Tenebras Lab", "apistate": "0.13", "url": "https://www.posttenebraslab.ch/status/status.json"}, {"name": "Chaostreff Chemnitz", "apistate": "0.13", "url": "https://chaoschemnitz.de/chch.json"}, {"name": "Garoa Hacker Clube", "apistate": "0.12", "url": "https://garoahc.appspot.com/status"}, {"name": "Hackspace Manchester", "apistate": "not available", "url": "http://spaceapi.hacman.org.uk/"}, {"name": "LeineLab", "apistate": "0.13", "url": "http://status.leinelab.org/api/spaceapi.json"}, {"name": "FAU FabLab", "apistate": "invalid", "url": "https://fablab.fau.de/spaceapi/"}, {"name": "HSMTY", "apistate": "not available", "url": "http://api.hsmty.org/status.json"}, {"name": "FIXME", "apistate": "0.13", "url": "https://fixme.ch/cgi-bin/spaceapi.py"}, {"name": "H.A.C.K.", "apistate": "0.13", "url": "https://vsza.hu/hacksense/spaceapi_status.json"}, {"name": "Tarlab", "apistate": "0.13", "url": "http://tarlab.fi/spaceapi/space.api"}, {"name": "LambdaSpace", "apistate": "not available", "url": "https://api.lambdaspace.gr/api/v2.0/SpaceAPI"}, {"name": "Le Loop", "apistate": "0.13", "url": "http://spaceapi.leloop.org/status.json"}, {"name": "GeekLabs", "apistate": "0.13", "url": "http://spaceapi.geeklabs.dk/?format=json"}, {"name": "Hackspace Siegen", "apistate": "invalid", "url": "https://status.hasi.it/spaceapi"}, {"name": "HTU Graz - E-Lab", "apistate": "0.13", "url": "http://edv-support.htu.tugraz.at/doorothy/elab/status.spaceapi"}, {"name": "Hackerspace Bremen e.V.", "apistate": "0.12", "url": "http://hackerspacehb.appspot.com/status"}, {"name": "mag.lab", "apistate": "0.13", "url": "https://state.maglab.space/spaceapi.json"}, {"name": "Milwaukee Makerspace", "apistate": "0.13", "url": "http://apps.2xlnetworks.net/milwaukeemakerspace/"}, {"name": "TDVenlo", "apistate": "0.13", "url": "https://tdvenlo.nl/spaceapi.json"}, {"name": "Hacklab", "apistate": "0.13", "url": "https://hacklab.kiev.ua/files/spaceapi.json"}, {"name": "Arch Reactor", "apistate": "invalid", "url": "https://archreactor.org/status.php"}, {"name": "Krautspace", "apistate": "0.13", "url": "https://status.kraut.space/api"}, {"name": "Hacksaar", "apistate": "0.13", "url": "http://spaceapi.hacksaar.de/status.json"}, {"name": "Maakplek", "apistate": "0.13", "url": "http://maakplek.nl/api/"}, {"name": "Makerspace Erfurt", "apistate": "0.13", "url": "https://status.makerspace-erfurt.de/status.json"}, {"name": "Pixelbar", "apistate": "0.13", "url": "https://spaceapi.pixelbar.nl/"}, {"name": "Hackerspace KRK", "apistate": "0.13", "url": "http://hskrk-spacemon.herokuapp.com"}, {"name": "Pangloss Labs #1", "apistate": "invalid", "url": "http://spaceapi.panglosslabs.org/spaceapi.json"}, {"name": "Matehackers", "apistate": "not available", "url": "http://mateaberto.herokuapp.com/status.json"}, {"name": "Hacklabor", "apistate": "0.13", "url": "https://hacklabor.de/api/space/v1/"}, {"name": "OpenLab Augsburg", "apistate": "0.13", "url": "http://api.openlab-augsburg.de/data.json"}, {"name": "Laboratoire Ouvert Grenoblois", "apistate": "0.13", "url": "https://www.logre.eu/spaceapi.json"}, {"name": "Netz39", "apistate": "0.13", "url": "http://spaceapi.n39.eu/json"}, {"name": "Maschinendeck", "apistate": "0.13", "url": "http://state.maschinendeck.org/spaceapi.json"}, {"name": "MetaMeute", "apistate": "0.12", "url": "https://status.metameute.de/spaceapi.json"}, {"name": "CCC Bremen", "apistate": "invalid", "url": "https://schalter.ccchb.de/spaceapi.json"}, {"name": "NURDSpace", "apistate": "0.13", "url": "http://space.nurdspace.nl/spaceapi/status.json"}, {"name": "MakeSpace Madrid", "apistate": "0.13", "url": "https://makespacemadrid.org/spaceapi/status.json"}, {"name": "Freies Labor", "apistate": "0.13", "url": "https://freieslabor.org/api/info"}, {"name": "Level2", "apistate": "0.13", "url": "https://www.hackerspace.lu/od/"}, {"name": "Hackerspace Nijmegen", "apistate": "0.13", "url": "https://hsnmgn.hacklabs.nl/apis/spacestate.php"}, {"name": "London Hackspace", "apistate": "0.13", "url": "https://london.hackspace.org.uk/spaceapi"}, {"name": "Motionlab", "apistate": "invalid", "url": "https://spaceapi.motionlab.berlin/"}, {"name": "Laboratorio Hacker de Campinas", "apistate": "0.13", "url": "http://lhc.net.br/spacenet.json"}, {"name": "LAG", "apistate": "0.13", "url": "https://state.laglab.org/spaceapi.json"}, {"name": "Ace Monster Toys", "apistate": "invalid", "url": "http://acemonstertoys.org/status.json"}, {"name": "Dingfabrik", "apistate": "not available", "url": "http://dingfabrik.de/status/spaceapi.php"}, {"name": "MidsouthMakers", "apistate": "invalid", "url": "http://midsouthmakers.org/spaceapi/"}, {"name": "Polytechnischer Werkraum Zittau", "apistate": "0.13", "url": "https://werkraum.freiraumzittau.de/spaceapi/13/"}, {"name": "VoidWarranties", "apistate": "0.13", "url": "http://spaceapi.voidwarranties.be"}, {"name": "HTU Graz - Basisgruppe Telematik", "apistate": "0.13", "url": "http://edv-support.htu.tugraz.at/doorothy/bagru/status.spaceapi"}, {"name": "Stratum 0", "apistate": "0.13", "url": "http://status.stratum0.org/status.json"}, {"name": "Noklab", "apistate": "0.13", "url": "https://cccgoe.de/spaceapi.php"}, {"name": "TkkrLab", "apistate": "invalid", "url": "http://tkkrlab.nl/statejson.php"}, {"name": "Root", "apistate": "not available", "url": "https://bot.rootclub.it:8081/spaceapi.json"}, {"name": "Heidelberg Makerspace", "apistate": "not available", "url": "https://heidelberg-makerspace.de/status.json"}, {"name": "Quelab", "apistate": "0.13", "url": "http://quelab.atomickiva.net/spaceapi.test"}, {"name": "Swansea Hackspace", "apistate": "0.13", "url": "http://swansea.hackspace.org.uk/spaceapi.php"}, {"name": "Mittelab", "apistate": "0.13", "url": "https://www.mittelab.org/status.json"}, {"name": "Makers Local 256", "apistate": "invalid", "url": "https://256.makerslocal.org/status.json"}, {"name": "IT-Syndikat", "apistate": "0.13", "url": "http://it-syndikat.org/api/status.php"}, {"name": "UrLab", "apistate": "0.13", "url": "https://urlab.be/spaceapi.json"}, {"name": "hackzogtum", "apistate": "0.13", "url": "https://spaceapi.hackzogtum-coburg.de"}, {"name": "vspace.one", "apistate": "invalid", "url": "https://vspace.one/spaceapi.json"}, {"name": "Open Space Aarhus", "apistate": "0.13", "url": "http://spaceapi.osaa.dk/status/json"}, {"name": "realraum", "apistate": "invalid", "url": "http://realraum.at/status.json"}, {"name": "brmlab", "apistate": "not available", "url": "http://nat.brmlab.cz/brmd/brmstatus.json"}, {"name": "Recompile", "apistate": "not available", "url": "http://www.recompile.se/spaceapi"}, {"name": "base48", "apistate": "0.12", "url": "https://48.io/status/"}, {"name": "HSBNE (Hackerspace Brisbane)", "apistate": "0.13", "url": "https://portal.hsbne.org/api/spacedirectory/"}, {"name": "Maschinenraum", "apistate": "0.12", "url": "http://api.maschinenraum.tk/status.json"}, {"name": "Mainframe", "apistate": "0.13", "url": "http://status.mainframe.io/api/spaceInfo"}, {"name": "Warpzone e.V.", "apistate": "0.13", "url": "https://api.warpzone.ms/spaceapi"}, {"name": "The Bodgery", "apistate": "0.13", "url": "http://thebodgery.org/bodgery_space.cgi"}, {"name": "spaceleft", "apistate": "not available", "url": "http://www.space-left.org/spaceapi13.json"}, {"name": "fNordeingang", "apistate": "0.13", "url": "https://fnord.istsystemrelevant.de/spaceapi.json"}, {"name": "HacDC", "apistate": "0.13", "url": "http://api.hacdc.org/status.php"}, {"name": "shackspace - stuttgart hackerspace", "apistate": "0.13", "url": "https://api.shackspace.de/v1/spaceapi"}, {"name": "Netzladen", "apistate": "0.13", "url": "http://netzladen.org/api/status.json"}, {"name": "syn2cat", "apistate": "0.13", "url": "https://level2.lu/spaceapi/"}, {"name": "UN-Hack-Bar", "apistate": "0.13", "url": "https://keinanschluss.un-hack-bar.de/spaceapi.json"}, {"name": "backspace", "apistate": "0.13", "url": "https://status.bckspc.de/spacestatus.php"}, {"name": "turmlabor", "apistate": "0.13", "url": "http://www.turmlabor.de/spaces.api"}, {"name": "RevSpace", "apistate": "invalid", "url": "http://revspace.nl/status/status.php"}, {"name": "Hackeriet", "apistate": "0.13", "url": "http://door.hackeriet.no/spaceapi.json"}, {"name": "Tampa Hackerspace", "apistate": "not available", "url": "http://spaceapi.tampahackerspace.com/"}, {"name": "see-base", "apistate": "0.13", "url": "https://bodensee.space/spaceapi/see-base.json"}, {"name": "[hsmr]", "apistate": "invalid", "url": "https://hsmr.cc/spaceapi.json"}, {"name": "verschwoerhaus", "apistate": "0.13", "url": "https://verschwoerhaus.de/feed/spaceapi"}, {"name": "Ko-Lab", "apistate": "invalid", "url": "https://ko-lab.space/spaceapi/"}, {"name": "flipdot", "apistate": "0.13", "url": "https://api.flipdot.org/"}, {"name": "Tangleball", "apistate": "0.13", "url": "http://www.tangleball.org.nz/wiki/index.php/Space_API?action=raw"}, {"name": "Munich Maker Lab", "apistate": "0.13", "url": "http://status.munichmakerlab.de/spaceapi.php"}, {"name": "TOG", "apistate": "not available", "url": "http://tog.ie/cgi-bin/space"}, {"name": "Nova Labs", "apistate": "0.13", "url": "http://nova-labs.org/api/"}, {"name": "P'y\u014fngyang Hackerspace", "apistate": "0.13", "url": "http://status.pyongyanghackerspace.org/jiwi.json"}, {"name": "nbsp", "apistate": "0.13", "url": "http://nobreakspace.org/status/spaceapi.json"}, {"name": "Wolfplex Hackerspace", "apistate": "0.13", "url": "https://api.wolfplex.be/space"}, {"name": "xHain", "apistate": "0.13", "url": "https://x-hain.de/spaceapi-0.13.json"}, {"name": "Toolbox Bodensee e.V.", "apistate": "0.13", "url": "https://bodensee.space/spaceapi/toolboxbodenseeev.json"}, {"name": "Ume\u00e5 Hackerspace", "apistate": "0.13", "url": "http://umeahackerspace.se:12345/spaceapi.json"}, {"name": "c-base", "apistate": "0.13", "url": "http://www.c-base.org/status.json"}, {"name": "Do It Yourself Werkstatt Wilhelmshaven", "apistate": "0.13", "url": "https://www.diyww.de/api/status"}, {"name": "Technologia Incognita", "apistate": "0.13", "url": "http://techinc.nl/space/spacestate.json"}, {"name": "nordlab e. V.", "apistate": "0.13", "url": "http://spaceapi.nordlab-ev.de"}, {"name": "z-Labor Zwickau", "apistate": "invalid", "url": "http://api.service.z-labor.space/spaceapi.json"}, {"name": "TechTonik Labs", "apistate": "0.13", "url": "https://raw.github.com/sbhackerspace/sbhx-spaceapi/master/spaceapi.json"}, {"name": "Sudo Room", "apistate": "0.12", "url": "http://api.sudoroom.org/status.json"}, {"name": "Nottinghack", "apistate": "0.13", "url": "http://lspace.nottinghack.org.uk/status/status.php"}, {"name": "bytewerk", "apistate": "0.13", "url": "http://stats.bytewerk.org/status.json"}, {"name": "Perth Artifactory", "apistate": "0.13", "url": "http://space.artifactory.org.au/spaceapi.json"}, {"name": "Minsk Hackerspace", "apistate": "0.13", "url": "http://hackerspace.by/spaceapi"}, {"name": "HeatSync Labs", "apistate": "0.12", "url": "http://members.heatsynclabs.org/space_api.json"}, {"name": "Warsaw Hackerspace", "apistate": "0.13", "url": "https://hackerspace.pl/spaceapi"}, {"name": "Forschung und Technik e.V.", "apistate": "invalid", "url": "https://spaceapi.futev.de/spaceapi.json"}, {"name": "init Lab", "apistate": "0.13", "url": "https://fauna.initlab.org/spaceapi/status.json"}, {"name": "C3D2", "apistate": "not available", "url": "https://www.c3d2.de/spaceapi.json"}, {"name": "MuCCC", "apistate": "0.13", "url": "http://api.muc.ccc.de/spaceapi.json"}, {"name": "Starship Factory", "apistate": "not available", "url": "http://spaceapi.apis.starship-factory.ch/api/spaceapi"}, {"name": "Hackerspace.gr", "apistate": "0.13", "url": "http://www.hackerspace.gr/spaceapi"}]